overturemaestro-0.5.0.dist-info/METADATA
overturemaestro-0.5.0.dist-info/WHEEL
overturemaestro-0.5.0.dist-info/entry_points.txt
overturemaestro-0.5.0.dist-info/licenses/LICENSE
overturemaestro/__init__.py
overturemaestro/__main__.py
overturemaestro/_constants.py
overturemaestro/_exceptions.py
overturemaestro/_geometry_clustering.py
overturemaestro/_parquet_multiprocessing.py
overturemaestro/_rich_progress.py
overturemaestro/advanced_functions/__init__.py
overturemaestro/advanced_functions/functions.py
overturemaestro/advanced_functions/poi.py
overturemaestro/advanced_functions/transportation.py
overturemaestro/advanced_functions/wide_form.py
overturemaestro/cache.py
overturemaestro/cli.py
overturemaestro/data_downloader.py
overturemaestro/elapsed_time_decorator.py
overturemaestro/functions.py
overturemaestro/geocode.py
overturemaestro/geopandas_io.py
overturemaestro/py.typed
overturemaestro/release_index.py
overturemaestro-0.5.0.dist-info/RECORD
