Metadata-Version: 2.1
Name: OvertureMaestro
Version: 0.5.0
Summary: An open-source tool for downloading Overture Maps data with quality of life features
Author-Email: Kamil Raczycki <kraczycki@kraina.ai>
License: Apache-2.0
Classifier: Development Status :: 3 - Alpha
Classifier: License :: OSI Approved :: Apache Software License
Classifier: Topic :: Scientific/Engineering :: Artificial Intelligence
Classifier: Topic :: Scientific/Engineering :: GIS
Classifier: Intended Audience :: Science/Research
Classifier: Intended Audience :: Developers
Classifier: Programming Language :: Python :: 3
Classifier: Programming Language :: Python :: 3.9
Classifier: Programming Language :: Python :: 3.10
Classifier: Programming Language :: Python :: 3.11
Classifier: Programming Language :: Python :: 3.12
Classifier: Operating System :: Unix
Classifier: Operating System :: MacOS
Classifier: Operating System :: Microsoft :: Windows
Requires-Python: >=3.9
Requires-Dist: overturemaps>=0.8.0
Requires-Dist: geopandas>=1.0
Requires-Dist: shapely>=2.0.6
Requires-Dist: pyarrow>=16.0.0
Requires-Dist: rich>=12.0.0
Requires-Dist: geoarrow-rust-core>=0.4.0
Requires-Dist: pooch>=1.6.0
Requires-Dist: aiohttp>=3.8.0
Requires-Dist: fsspec>=2021.04.0
Requires-Dist: geopy>=2.0.0
Requires-Dist: numpy>=1.26.0
Requires-Dist: duckdb>=1.1.2
Requires-Dist: psutil>=5.6.2
Requires-Dist: polars>=1.9
Requires-Dist: rq_geo_toolkit>=2025.8.0
Provides-Extra: cli
Requires-Dist: typer[all]>=0.9.0; extra == "cli"
Requires-Dist: h3>=4.0.0b1; extra == "cli"
Requires-Dist: s2>=0.1.9; extra == "cli"
Requires-Dist: python-geohash>=0.8; extra == "cli"
Provides-Extra: index-generation
Requires-Dist: scikit-learn>=1.0; extra == "index-generation"
